[
  {
    "precinct": "001",
    "name": "Harbins A",
    "location": "Harbins Elementary (GCPS)",
    "address": "3550 New Hope Road",
    "city": "Dacula",
    "state": "GA",
    "zip": "30019",
    "full_address": "3550 New Hope Road, Dacula, GA 30019",
    "lat": 33.943233553427,
    "lon": -83.855664322347
  },
  {
    "precinct": "002",
    "name": "Rockbridge A",
    "location": "Annistown Elementary (GCPS)",
    "address": "3150 Spain Road",
    "city": "Snellville",
    "state": "GA",
    "zip": "30039",
    "full_address": "3150 Spain Road, Snellville, GA 30039",
    "lat": 33.802260111165,
    "lon": -84.070349264684
  },
  {
    "precinct": "003",
    "name": "Dacula",
    "location": "Dacula UMC",
    "address": "2655 Fence Rd. NE",
    "city": "Dacula",
    "state": "GA",
    "zip": "30019",
    "full_address": "2655 Fence Rd. NE, Dacula, GA 30019",
    "lat": 34.003361892178,
    "lon": -83.902202213357
  },
  {
    "precinct": "004",
    "name": "Suwanee A",
    "location": "Suwanee Branch GC Public Library",
    "address": "361 Main Street",
    "city": "Suwanee",
    "state": "GA",
    "zip": "30024",
    "full_address": "361 Main Street, Suwanee, GA 30024",
    "lat": 34.0575987,
    "lon": -84.0672514
  },
  {
    "precinct": "005",
    "name": "Baycreek A",
    "location": "Grayson United Methodist Church",
    "address": "555 Grayson Parkway",
    "city": "Grayson",
    "state": "GA",
    "zip": "30017",
    "full_address": "555 Grayson Parkway, Grayson, GA 30017",
    "lat": 33.89151892228,
    "lon": -83.961516503998
  },
  {
    "precinct": "006",
    "name": "Goodwins A",
    "location": "McKendree UMC",
    "address": "1570 Lawrenceville Suwanee Road",
    "city": "Lawrenceville",
    "state": "GA",
    "zip": "30043",
    "full_address": "1570 Lawrenceville Suwanee Road, Lawrenceville, GA 30043",
    "lat": 33.98959986965,
    "lon": -84.029100220513
  },
  {
    "precinct": "007",
    "name": "Duluth A",
    "location": "Duluth City Hall",
    "address": "3167 Main Street NW",
    "city": "Duluth",
    "state": "GA",
    "zip": "30096",
    "full_address": "3167 Main Street NW, Duluth, GA 30096",
    "lat": 34.002427496011,
    "lon": -84.145566564598
  },
  {
    "precinct": "008",
    "name": "Duncans A",
    "location": "Frank Osborne Middle School",
    "address": "4404 Braselton Highway",
    "city": "Hoschton",
    "state": "GA",
    "zip": "30548",
    "full_address": "4404 Braselton Highway, Hoschton, GA 30548",
    "lat": 34.076701950347,
    "lon": -83.878049047904
  },
  {
    "precinct": "009",
    "name": "Picketts A",
    "location": "Bogan Park Community Center (GC Park)",
    "address": "2723 N Bogan Road",
    "city": "Buford",
    "state": "GA",
    "zip": "30519",
    "full_address": "2723 N Bogan Road, Buford, GA 30519",
    "lat": 34.109431482825,
    "lon": -83.969718449987
  },
  {
    "precinct": "010",
    "name": "Cates A",
    "location": "Snellville Community Church",
    "address": "2428 Main Street East",
    "city": "Snellville",
    "state": "GA",
    "zip": "30078",
    "full_address": "2428 Main Street East, Snellville, GA 30078",
    "lat": 33.856449891599,
    "lon": -84.015824600106
  },
  {
    "precinct": "011",
    "name": "Berkshire A",
    "location": "Church on a Hill",
    "address": "5255 Hwy 29",
    "city": "Lilburn",
    "state": "GA",
    "zip": "30047",
    "full_address": "5255 Hwy 29, Lilburn, GA 30047",
    "lat": 33.8887957,
    "lon": -84.1559103
  },
  {
    "precinct": "012",
    "name": "Berkshire B",
    "location": "Lucky Shoals Park Community Recreation Center",
    "address": "4651 Britt Road",
    "city": "Norcross",
    "state": "GA",
    "zip": "30093",
    "full_address": "4651 Britt Road, Norcross, GA 30093",
    "lat": 33.880850660964,
    "lon": -84.201182044026
  },
  {
    "precinct": "013",
    "name": "Duncans C",
    "location": "Hamilton Mill UMC",
    "address": "1450 Pine Road",
    "city": "Dacula",
    "state": "GA",
    "zip": "30019",
    "full_address": "1450 Pine Road, Dacula, GA 30019",
    "lat": 34.057234091065,
    "lon": -83.888261853413
  },
  {
    "precinct": "014",
    "name": "Garners A",
    "location": "Mountain Park Depot (GC Park)",
    "address": "5050 Five Forks Trickum Road",
    "city": "Lilburn",
    "state": "GA",
    "zip": "30047",
    "full_address": "5050 Five Forks Trickum Road, Lilburn, GA 30047",
    "lat": 33.847926535191,
    "lon": -84.119584667061
  },
  {
    "precinct": "015",
    "name": "Lawrenceville A",
    "location": "Lawrenceville First Baptist Church",
    "address": "165 Clayton Street",
    "city": "Lawrenceville",
    "state": "GA",
    "zip": "30046",
    "full_address": "165 Clayton Street, Lawrenceville, GA 30046",
    "lat": 33.956795218652,
    "lon": -83.988465450711
  },
  {
    "precinct": "016",
    "name": "Lawrenceville B",
    "location": "Gwinnett County Fairgrounds",
    "address": "2405 Sugarloaf Parkway",
    "city": "Lawrenceville",
    "state": "GA",
    "zip": "30045",
    "full_address": "2405 Sugarloaf Parkway, Lawrenceville, GA 30045",
    "lat": 33.917605987236,
    "lon": -83.987829667104
  },
  {
    "precinct": "017",
    "name": "Martins A",
    "location": "GSMST (GCPS)",
    "address": "970 McElvaney Lane",
    "city": "Lawrenceville",
    "state": "GA",
    "zip": "30044",
    "full_address": "970 McElvaney Lane, Lawrenceville, GA 30044",
    "lat": 33.952651953568,
    "lon": -84.059808528317
  },
  {
    "precinct": "018",
    "name": "Martins B",
    "location": "New Hope Christian Church",
    "address": "1982 Old Norcross Road",
    "city": "Lawrenceville",
    "state": "GA",
    "zip": "30044",
    "full_address": "1982 Old Norcross Road, Lawrenceville, GA 30044",
    "lat": 33.951334595838,
    "lon": -84.061675682164
  },
  {
    "precinct": "019",
    "name": "Martins C",
    "location": "The Nett Church @ Bethesda",
    "address": "444 Bethesda Church Road",
    "city": "Lawrenceville",
    "state": "GA",
    "zip": "30044",
    "full_address": "444 Bethesda Church Road, Lawrenceville, GA 30044",
    "lat": 33.920673388653,
    "lon": -84.084551487855
  },
  {
    "precinct": "020",
    "name": "Pinckneyville A",
    "location": "Summerour Middle (GCPS)",
    "address": "321 Price Place",
    "city": "Norcross",
    "state": "GA",
    "zip": "30071",
    "full_address": "321 Price Place, Norcross, GA 30071",
    "lat": 33.941321702882,
    "lon": -84.203408195412
  },
  {
    "precinct": "021",
    "name": "Pinckneyville B",
    "location": "Rockbridge Elementary (GCPS)",
    "address": "6066 Rockbridge School Road",
    "city": "Norcross",
    "state": "GA",
    "zip": "30093",
    "full_address": "6066 Rockbridge School Road, Norcross, GA 30093",
    "lat": 33.898091241679,
    "lon": -84.197738568239
  },
  {
    "precinct": "022",
    "name": "Pinckneyville C",
    "location": "Peachtree Elementary (GCPS)",
    "address": "5995 Crooked Creek Rd",
    "city": "Peachtree Corners",
    "state": "GA",
    "zip": "30092",
    "full_address": "5995 Crooked Creek Rd, Peachtree Corners, GA 30092",
    "lat": 33.962058526105,
    "lon": -84.236840398159
  },
  {
    "precinct": "023",
    "name": "Pinckneyville D",
    "location": "Meadowcreek Elementary (GCPS)",
    "address": "5025 Georgia Belle Court",
    "city": "Norcross",
    "state": "GA",
    "zip": "30093",
    "full_address": "5025 Georgia Belle Court, Norcross, GA 30093",
    "lat": 33.920995629537,
    "lon": -84.167706934082
  },
  {
    "precinct": "024",
    "name": "Sugar Hill A",
    "location": "Buford City Hall",
    "address": "2300 Buford Highway",
    "city": "Buford",
    "state": "GA",
    "zip": "30518",
    "full_address": "2300 Buford Highway, Buford, GA 30518",
    "lat": 34.114907054614,
    "lon": -83.994729157405
  },
  {
    "precinct": "025",
    "name": "Sugar Hill B",
    "location": "Calvary Assembly Church of God",
    "address": "1132 Buford Hwy",
    "city": "Sugar Hill",
    "state": "GA",
    "zip": "30518",
    "full_address": "1132 Buford Hwy, Sugar Hill, GA 30518",
    "lat": 34.034376699896,
    "lon": -84.088184493262
  },
  {
    "precinct": "026",
    "name": "Hog Mountain A",
    "location": "Rock Springs UMC",
    "address": "1100 Rock Springs Road",
    "city": "Lawrenceville",
    "state": "GA",
    "zip": "30043",
    "full_address": "1100 Rock Springs Road, Lawrenceville, GA 30043",
    "lat": 34.047881092742,
    "lon": -83.999313867609
  },
  {
    "precinct": "027",
    "name": "Hog Mountain B",
    "location": "Prospect UMC",
    "address": "1549 Prospect Road",
    "city": "Lawrenceville",
    "state": "GA",
    "zip": "30043",
    "full_address": "1549 Prospect Road, Lawrenceville, GA 30043",
    "lat": 34.021059791001,
    "lon": -83.960952961754
  },
  {
    "precinct": "028",
    "name": "Rockycreek A",
    "location": "Mulberry Elementary School (GCPS)",
    "address": "442 E Union Grove Cir",
    "city": "Auburn",
    "state": "GA",
    "zip": "30011",
    "full_address": "442 E Union Grove Cir, Auburn, GA 30011",
    "lat": 34.032434372965,
    "lon": -83.861934449818
  },
  {
    "precinct": "029",
    "name": "Cates B",
    "location": "Five Forks Library",
    "address": "2780 Five Forks Trickum Road",
    "city": "Lawrenceville",
    "state": "GA",
    "zip": "30044",
    "full_address": "2780 Five Forks Trickum Road, Lawrenceville, GA 30044",
    "lat": 33.8932861,
    "lon": -84.0549201
  },
  {
    "precinct": "030",
    "name": "Cates C",
    "location": "Britt Elementary (GCPS)",
    "address": "2503 Skyland Drive",
    "city": "Snellville",
    "state": "GA",
    "zip": "30078",
    "full_address": "2503 Skyland Drive, Snellville, GA 30078",
    "lat": 33.85521914572,
    "lon": -84.010571209632
  },
  {
    "precinct": "031",
    "name": "Hog Mountain D",
    "location": "Woodward Mill Elementary (GCPS)",
    "address": "2020 Buford Drive",
    "city": "Lawrenceville",
    "state": "GA",
    "zip": "30043",
    "full_address": "2020 Buford Drive, Lawrenceville, GA 30043",
    "lat": 34.021448329387,
    "lon": -83.98649891518
  },
  {
    "precinct": "032",
    "name": "Berkshire D",
    "location": "New Mercies Christian Church",
    "address": "4000 Five Forks Trickum Rd",
    "city": "Lilburn",
    "state": "GA",
    "zip": "30047",
    "full_address": "4000 Five Forks Trickum Rd, Lilburn, GA 30047",
    "lat": 33.869785852487,
    "lon": -84.09024571834
  },
  {
    "precinct": "033",
    "name": "Berkshire E",
    "location": "Arcado Elementary (GCPS)",
    "address": "5150 Arcado Road SW",
    "city": "Lilburn",
    "state": "GA",
    "zip": "30047",
    "full_address": "5150 Arcado Road SW, Lilburn, GA 30047",
    "lat": 33.872182246423,
    "lon": -84.141799519558
  },
  {
    "precinct": "034",
    "name": "Berkshire F",
    "location": "Lilburn Christian Church",
    "address": "314 Arcado Road",
    "city": "Lilburn",
    "state": "GA",
    "zip": "30047",
    "full_address": "314 Arcado Road, Lilburn, GA 30047",
    "lat": 33.902152682674,
    "lon": -84.120687074203
  },
  {
    "precinct": "035",
    "name": "Cates D",
    "location": "Berean Baptist Church",
    "address": "1405 Hewatt Road",
    "city": "Lilburn",
    "state": "GA",
    "zip": "30047",
    "full_address": "1405 Hewatt Road, Lilburn, GA 30047",
    "lat": 33.872282522234,
    "lon": -84.053287451626
  },
  {
    "precinct": "036",
    "name": "Cates E",
    "location": "Trinity Lutheran Church",
    "address": "1826 Killian Hill Rd",
    "city": "Lilburn",
    "state": "GA",
    "zip": "30047",
    "full_address": "1826 Killian Hill Rd, Lilburn, GA 30047",
    "lat": 33.847736063874,
    "lon": -84.074105406908
  },
  {
    "precinct": "037",
    "name": "Pinckneyville E",
    "location": "Winters Chapel United Methodist Church",
    "address": "5105 Winters Chapel Road",
    "city": "Atlanta",
    "state": "GA",
    "zip": "30360",
    "full_address": "5105 Winters Chapel Road, Atlanta, GA 30360",
    "lat": 33.946765049318,
    "lon": -84.269914771934
  },
  {
    "precinct": "038",
    "name": "Pinckneyville F",
    "location": "Best Friend Park (GC Park)",
    "address": "6224 Jimmy Carter Blvd",
    "city": "Norcross",
    "state": "GA",
    "zip": "30071",
    "full_address": "6224 Jimmy Carter Blvd, Norcross, GA 30071",
    "lat": 33.92793614913,
    "lon": -84.219981840278
  },
  {
    "precinct": "039",
    "name": "Duncans D",
    "location": "Hamilton Mill Christian Church",
    "address": "3809 Sardis Church Road",
    "city": "Buford",
    "state": "GA",
    "zip": "30519",
    "full_address": "3809 Sardis Church Road, Buford, GA 30519",
    "lat": 34.083363069212,
    "lon": -83.908463711987
  },
  {
    "precinct": "040",
    "name": "Pinckneyville H",
    "location": "Pinckneyville Community Center (GC Park)",
    "address": "4650 Peachtree Industrial Blvd",
    "city": "Norcross",
    "state": "GA",
    "zip": "30071",
    "full_address": "4650 Peachtree Industrial Blvd, Norcross, GA 30071",
    "lat": 33.972151278936,
    "lon": -84.185681196095
  },
  {
    "precinct": "041",
    "name": "Baycreek B",
    "location": "Peachcrest Christian Church",
    "address": "4100 Rosebud Road",
    "city": "Loganville",
    "state": "GA",
    "zip": "30052",
    "full_address": "4100 Rosebud Road, Loganville, GA 30052",
    "lat": 33.822971622115,
    "lon": -83.960601686032
  },
  {
    "precinct": "042",
    "name": "Lawrenceville C",
    "location": "Dyer Elementary School (GCPS)",
    "address": "1707 Hurricane Shoals Road",
    "city": "Dacula",
    "state": "GA",
    "zip": "30019",
    "full_address": "1707 Hurricane Shoals Road, Dacula, GA 30019",
    "lat": 33.996062054112,
    "lon": -83.936492014077
  },
  {
    "precinct": "043",
    "name": "Martins D",
    "location": "Sweetwater Middle (GCPS)",
    "address": "3500 Cruse Road",
    "city": "Lawrenceville",
    "state": "GA",
    "zip": "30044",
    "full_address": "3500 Cruse Road, Lawrenceville, GA 30044",
    "lat": 33.927592922017,
    "lon": -84.107710618956
  },
  {
    "precinct": "044",
    "name": "Rockbridge B",
    "location": "Centerville Elementary (GCPS)",
    "address": "3115 Centerville Hwy",
    "city": "Snellville",
    "state": "GA",
    "zip": "30039",
    "full_address": "3115 Centerville Hwy, Snellville, GA 30039",
    "lat": 33.804979061924,
    "lon": -84.008288642661
  },
  {
    "precinct": "045",
    "name": "Garners B",
    "location": "Shiloh Elementary (GCPS)",
    "address": "2400 Ross Road",
    "city": "Snellville",
    "state": "GA",
    "zip": "30039",
    "full_address": "2400 Ross Road, Snellville, GA 30039",
    "lat": 33.8467,
    "lon": -84.0118
  },
  {
    "precinct": "046",
    "name": "Cates F",
    "location": "Mountain Oak Baptist Church",
    "address": "2849 Mountain View Road",
    "city": "Snellville",
    "state": "GA",
    "zip": "30078",
    "full_address": "2849 Mountain View Road, Snellville, GA 30078",
    "lat": 33.869551330532,
    "lon": -84.036483431972
  },
  {
    "precinct": "047",
    "name": "Cates G",
    "location": "Cannon UMC",
    "address": "2424 Webb Gin House Road",
    "city": "Snellville",
    "state": "GA",
    "zip": "30078",
    "full_address": "2424 Webb Gin House Road, Snellville, GA 30078",
    "lat": 33.887226654849,
    "lon": -84.036894890424
  },
  {
    "precinct": "048",
    "name": "Duluth B",
    "location": "Mason Elementary (GCPS)",
    "address": "3030 Bunten Road",
    "city": "Duluth",
    "state": "GA",
    "zip": "30096",
    "full_address": "3030 Bunten Road, Duluth, GA 30096",
    "lat": 33.993659838281,
    "lon": -84.119313018896
  },
  {
    "precinct": "049",
    "name": "Garners C",
    "location": "Lucerne Baptist Church",
    "address": "4805 Stone Mountain Hwy",
    "city": "Lilburn",
    "state": "GA",
    "zip": "30047",
    "full_address": "4805 Stone Mountain Hwy, Lilburn, GA 30047",
    "lat": 33.82725849562,
    "lon": -84.096292452687
  },
  {
    "precinct": "050",
    "name": "Pinckneyville I",
    "location": "Beaver Ridge Elementary (GCPS)",
    "address": "1978 Beaver Ruin Road",
    "city": "Norcross",
    "state": "GA",
    "zip": "30071",
    "full_address": "1978 Beaver Ruin Road, Norcross, GA 30071",
    "lat": 33.93363527597,
    "lon": -84.173380355592
  },
  {
    "precinct": "051",
    "name": "Pinckneyville J",
    "location": "Iglesia Metropolitana Seventh Day Adventist",
    "address": "5990 Oakbrook Parkway",
    "city": "Norcross",
    "state": "GA",
    "zip": "30093",
    "full_address": "5990 Oakbrook Parkway, Norcross, GA 30093",
    "lat": 33.912376643669,
    "lon": -84.202776795246
  },
  {
    "precinct": "052",
    "name": "Berkshire G",
    "location": "Mountain Park Activity Building (GC Park)",
    "address": "1063 Rockbridge Road",
    "city": "Stone Mountain",
    "state": "GA",
    "zip": "30087",
    "full_address": "1063 Rockbridge Road, Stone Mountain, GA 30087",
    "lat": 33.847107626366,
    "lon": -84.133932722447
  },
  {
    "precinct": "053",
    "name": "Cates H",
    "location": "T.W. Briscoe Park Main Building (Snellville Park)",
    "address": "2500 Sawyer Pkwy",
    "city": "Snellville",
    "state": "GA",
    "zip": "30078",
    "full_address": "2500 Sawyer Pkwy, Snellville, GA 30078",
    "lat": 33.840963343586,
    "lon": -84.010117009421
  },
  {
    "precinct": "054",
    "name": "Sugar Hill C",
    "location": "New Prospect UMC",
    "address": "2018 Buford Dam Road",
    "city": "Buford",
    "state": "GA",
    "zip": "30518",
    "full_address": "2018 Buford Dam Road, Buford, GA 30518",
    "lat": 34.145566831222,
    "lon": -84.026666326623
  },
  {
    "precinct": "055",
    "name": "Sugar Hill D",
    "location": "Lanier Middle School",
    "address": "6482 Suwanee Dam Rd",
    "city": "Buford",
    "state": "GA",
    "zip": "30518",
    "full_address": "6482 Suwanee Dam Rd, Buford, GA 30518",
    "lat": 34.146740656793,
    "lon": -84.0626266962
  },
  {
    "precinct": "056",
    "name": "Duluth C",
    "location": "Duluth Festival Center",
    "address": "3142 Hill Street",
    "city": "Duluth",
    "state": "GA",
    "zip": "30096",
    "full_address": "3142 Hill Street, Duluth, GA 30096",
    "lat": 34.00348306474,
    "lon": -84.145814887402
  },
  {
    "precinct": "057",
    "name": "Duluth D",
    "location": "BB Harris Elementary (GCPS)",
    "address": "3123 Claiborne Drive",
    "city": "Duluth",
    "state": "GA",
    "zip": "30096",
    "full_address": "3123 Claiborne Drive, Duluth, GA 30096",
    "lat": 33.986152426045,
    "lon": -84.13383668779
  },
  {
    "precinct": "058",
    "name": "Pinckneyville K",
    "location": "Beaver Ruin Road Baptist Church",
    "address": "1200 Beaver Ruin Road",
    "city": "Norcross",
    "state": "GA",
    "zip": "30093",
    "full_address": "1200 Beaver Ruin Road, Norcross, GA 30093",
    "lat": 33.924526476671,
    "lon": -84.138047315964
  },
  {
    "precinct": "059",
    "name": "Pinckneyville N",
    "location": "Landmark Church",
    "address": "3737 Holcomb Bridge Road",
    "city": "Norcross",
    "state": "GA",
    "zip": "30092",
    "full_address": "3737 Holcomb Bridge Road, Norcross, GA 30092",
    "lat": 33.960437037477,
    "lon": -84.248400718422
  },
  {
    "precinct": "060",
    "name": "Lawrenceville D",
    "location": "Rhodes Jordan Community Center (GC Park)",
    "address": "100 E Crogan Street",
    "city": "Lawrenceville",
    "state": "GA",
    "zip": "30046",
    "full_address": "100 E Crogan Street, Lawrenceville, GA 30046",
    "lat": 33.95650671704,
    "lon": -83.98475075538
  },
  {
    "precinct": "061",
    "name": "Lawrenceville E",
    "location": "Lawrenceville First UMC",
    "address": "395 W. Crogan Street",
    "city": "Lawrenceville",
    "state": "GA",
    "zip": "30046",
    "full_address": "395 W. Crogan Street, Lawrenceville, GA 30046",
    "lat": 33.95607717873,
    "lon": -83.991504502062
  },
  {
    "precinct": "062",
    "name": "Pinckneyville L",
    "location": "Peachtree Corners Baptist Church",
    "address": "4480 Peachtree Corners Circle",
    "city": "Norcross",
    "state": "GA",
    "zip": "30092",
    "full_address": "4480 Peachtree Corners Circle, Norcross, GA 30092",
    "lat": 33.977448368248,
    "lon": -84.228558537345
  },
  {
    "precinct": "063",
    "name": "Pinckneyville M",
    "location": "Simpson Elementary (GCPS)",
    "address": "4525 E. Jones Bridge Road",
    "city": "Norcross",
    "state": "GA",
    "zip": "30092",
    "full_address": "4525 E. Jones Bridge Road, Norcross, GA 30092",
    "lat": 33.99768554507,
    "lon": -84.229562213429
  },
  {
    "precinct": "064",
    "name": "Garners D",
    "location": "Mountain Park UMC",
    "address": "1405 Rockbridge Road",
    "city": "Stone Mountain",
    "state": "GA",
    "zip": "30087",
    "full_address": "1405 Rockbridge Road, Stone Mountain, GA 30087",
    "lat": 33.836176423607,
    "lon": -84.129241811507
  },
  {
    "precinct": "065",
    "name": "Berkshire H",
    "location": "Church on a Hill",
    "address": "5255 Hwy 29",
    "city": "Lilburn",
    "state": "GA",
    "zip": "30047",
    "full_address": "5255 Hwy 29, Lilburn, GA 30047",
    "lat": 33.8887957,
    "lon": -84.1559103
  },
  {
    "precinct": "066",
    "name": "Pinckneyville O",
    "location": "Atlanta Chinese Christian Church",
    "address": "4434 Britt Road",
    "city": "Tucker",
    "state": "GA",
    "zip": "30084",
    "full_address": "4434 Britt Road, Tucker, GA 30084",
    "lat": 33.882205132579,
    "lon": -84.208126179857
  },
  {
    "precinct": "067",
    "name": "Pucketts E",
    "location": "Patrick Elementary (GCPS)",
    "address": "2707 Kilgore Road",
    "city": "Buford",
    "state": "GA",
    "zip": "30519",
    "full_address": "2707 Kilgore Road, Buford, GA 30519",
    "lat": 34.089145518194,
    "lon": -83.961207189194
  },
  {
    "precinct": "068",
    "name": "Cates I",
    "location": "Oak Road Lutheran Church",
    "address": "1004 Oak Rd SW",
    "city": "Lilburn",
    "state": "GA",
    "zip": "30047",
    "full_address": "1004 Oak Rd SW, Lilburn, GA 30047",
    "lat": 33.883654152567,
    "lon": -84.057896867993
  },
  {
    "precinct": "069",
    "name": "Cates J",
    "location": "Good Shepherd Presbyterian Church",
    "address": "1400 Killian Hill Road",
    "city": "Lilburn",
    "state": "GA",
    "zip": "30047",
    "full_address": "1400 Killian Hill Road, Lilburn, GA 30047",
    "lat": 33.859360086019,
    "lon": -84.081940492962
  },
  {
    "precinct": "070",
    "name": "Goodwins B",
    "location": "Collins Hill Library",
    "address": "455 Camp Perrin Road",
    "city": "Lawrenceville",
    "state": "GA",
    "zip": "30043",
    "full_address": "455 Camp Perrin Road, Lawrenceville, GA 30043",
    "lat": 34.015594198682,
    "lon": -84.003683912399
  },
  {
    "precinct": "071",
    "name": "Lawrenceville F",
    "location": "Jordan Middle School (GCPS)",
    "address": "8 Village Way SE",
    "city": "Lawrenceville",
    "state": "GA",
    "zip": "30046",
    "full_address": "8 Village Way SE, Lawrenceville, GA 30046",
    "lat": 33.963346157477,
    "lon": -83.96512431557
  },
  {
    "precinct": "072",
    "name": "Martins E",
    "location": "Ferguson Elementary (GCPS)",
    "address": "1755 Centerview Drive",
    "city": "Duluth",
    "state": "GA",
    "zip": "30096",
    "full_address": "1755 Centerview Drive, Duluth, GA 30096",
    "lat": 33.951298907293,
    "lon": -84.123302506196
  },
  {
    "precinct": "073",
    "name": "Pinckneyville P",
    "location": "Unity Atlanta Church",
    "address": "3597 Parkway Lane",
    "city": "Peachtree Corners",
    "state": "GA",
    "zip": "30092",
    "full_address": "3597 Parkway Lane, Peachtree Corners, GA 30092",
    "lat": 33.959768484264,
    "lon": -84.231129199772
  },
  {
    "precinct": "074",
    "name": "Pinckneyville Q",
    "location": "Beaver Ruin Road Baptist Church",
    "address": "1200 Beaver Ruin Road",
    "city": "Norcross",
    "state": "GA",
    "zip": "30093",
    "full_address": "1200 Beaver Ruin Road, Norcross, GA 30093",
    "lat": 33.924526476671,
    "lon": -84.138047315964
  },
  {
    "precinct": "075",
    "name": "Rockbridge C",
    "location": "Zoar United Methodist Church",
    "address": "3895 Zoar Church Road",
    "city": "Snellville",
    "state": "GA",
    "zip": "30039",
    "full_address": "3895 Zoar Church Road, Snellville, GA 30039",
    "lat": 33.809632214579,
    "lon": -84.045576444324
  },
  {
    "precinct": "076",
    "name": "Rockbridge D",
    "location": "Evangel Community Church",
    "address": "3857 Centerville-Rosebud Road",
    "city": "Snellville",
    "state": "GA",
    "zip": "30039",
    "full_address": "3857 Centerville-Rosebud Road, Snellville, GA 30039",
    "lat": 33.804273802371,
    "lon": -84.038451932943
  },
  {
    "precinct": "077",
    "name": "Goodwins C",
    "location": "Gwinnett Church of Christ",
    "address": "1736 Sever Road",
    "city": "Lawrenceville",
    "state": "GA",
    "zip": "30043",
    "full_address": "1736 Sever Road, Lawrenceville, GA 30043",
    "lat": 33.981874747577,
    "lon": -84.055649800941
  },
  {
    "precinct": "078",
    "name": "Baycreek K",
    "location": "Grayson United Methodist Church",
    "address": "555 Grayson Pkwy",
    "city": "Grayson",
    "state": "GA",
    "zip": "30017",
    "full_address": "555 Grayson Pkwy, Grayson, GA 30017",
    "lat": 33.89151892228,
    "lon": -83.961516503998
  },
  {
    "precinct": "079",
    "name": "Cates K",
    "location": "Gwinnett Community Church",
    "address": "2516 Five Forks Trickum Rd",
    "city": "Lawrenceville",
    "state": "GA",
    "zip": "30044",
    "full_address": "2516 Five Forks Trickum Rd, Lawrenceville, GA 30044",
    "lat": 33.90000543737,
    "lon": -84.049503887256
  },
  {
    "precinct": "080",
    "name": "Baycreek C",
    "location": "Grace-New Hope Church",
    "address": "1766 New Hope Rd",
    "city": "Lawrenceville",
    "state": "GA",
    "zip": "30045",
    "full_address": "1766 New Hope Rd, Lawrenceville, GA 30045",
    "lat": 33.92354355104,
    "lon": -83.917878828478
  },
  {
    "precinct": "081",
    "name": "Cates L",
    "location": "Britt Elementary (GCPS)",
    "address": "2503 Skyland Drive",
    "city": "Snellville",
    "state": "GA",
    "zip": "30078",
    "full_address": "2503 Skyland Drive, Snellville, GA 30078",
    "lat": 33.85521914572,
    "lon": -84.010571209632
  },
  {
    "precinct": "082",
    "name": "Duluth E",
    "location": "Pleasant Hill Presbyterian Church",
    "address": "3700 Pleasant Hill Road",
    "city": "Duluth",
    "state": "GA",
    "zip": "30096",
    "full_address": "3700 Pleasant Hill Road, Duluth, GA 30096",
    "lat": 33.995433211011,
    "lon": -84.162465729588
  },
  {
    "precinct": "083",
    "name": "Goodwins D",
    "location": "Richland Homeowners Clubhouse",
    "address": "2074 Quinton Place",
    "city": "Suwanee",
    "state": "GA",
    "zip": "30024",
    "full_address": "2074 Quinton Place, Suwanee, GA 30024",
    "lat": 34.005105354676,
    "lon": -84.02537235567
  },
  {
    "precinct": "084",
    "name": "Lawrenceville G",
    "location": "First Christian Church",
    "address": "3495 Sugarloaf Pkwy",
    "city": "Lawrenceville",
    "state": "GA",
    "zip": "30044",
    "full_address": "3495 Sugarloaf Pkwy, Lawrenceville, GA 30044",
    "lat": 33.925034458509,
    "lon": -84.018960444607
  },
  {
    "precinct": "085",
    "name": "Lawrenceville H",
    "location": "Creekland Middle (GCPS)",
    "address": "170 Russell Road",
    "city": "Lawrenceville",
    "state": "GA",
    "zip": "30044",
    "full_address": "170 Russell Road, Lawrenceville, GA 30044",
    "lat": 33.998604170845,
    "lon": -84.017835475266
  },
  {
    "precinct": "086",
    "name": "Martins F",
    "location": "Corley Elementary (GCPS)",
    "address": "1331 Pleasant Hill Road",
    "city": "Lawrenceville",
    "state": "GA",
    "zip": "30044",
    "full_address": "1331 Pleasant Hill Road, Lawrenceville, GA 30044",
    "lat": 33.936614812922,
    "lon": -84.120857082341
  },
  {
    "precinct": "087",
    "name": "Pinckneyville S",
    "location": "Saint Patrick's Catholic Church",
    "address": "2140 Beaver Ruin Road",
    "city": "Norcross",
    "state": "GA",
    "zip": "30071",
    "full_address": "2140 Beaver Ruin Road, Norcross, GA 30071",
    "lat": 33.936995524903,
    "lon": -84.18571358203
  },
  {
    "precinct": "088",
    "name": "Rockbridge E",
    "location": "Redeemer Church",
    "address": "3750 Zoar Church Road SW",
    "city": "Snellville",
    "state": "GA",
    "zip": "30039",
    "full_address": "3750 Zoar Church Road SW, Snellville, GA 30039",
    "lat": 33.810557852645,
    "lon": -84.041045379919
  },
  {
    "precinct": "089",
    "name": "Sugar Hill E",
    "location": "Lanier High School (GCPS)",
    "address": "918 Buford Hwy",
    "city": "Sugar Hill",
    "state": "GA",
    "zip": "30518",
    "full_address": "918 Buford Hwy, Sugar Hill, GA 30518",
    "lat": 34.084337089506,
    "lon": -84.031580633216
  },
  {
    "precinct": "090",
    "name": "Lawrenceville I",
    "location": "Fairview Presbyterian Church",
    "address": "857 Duluth Hwy",
    "city": "Lawrenceville",
    "state": "GA",
    "zip": "30043",
    "full_address": "857 Duluth Hwy, Lawrenceville, GA 30043",
    "lat": 33.967606397577,
    "lon": -84.018811243242
  },
  {
    "precinct": "091",
    "name": "Baycreek D",
    "location": "First Baptist Church of Grayson",
    "address": "2142 Loganville Hwy",
    "city": "Grayson",
    "state": "GA",
    "zip": "30017",
    "full_address": "2142 Loganville Hwy, Grayson, GA 30017",
    "lat": 33.893648964964,
    "lon": -83.954229861334
  },
  {
    "precinct": "092",
    "name": "Berkshire J",
    "location": "Jubilee Christian Church International",
    "address": "701 Cole Drive",
    "city": "Lilburn",
    "state": "GA",
    "zip": "30047",
    "full_address": "701 Cole Drive, Lilburn, GA 30047",
    "lat": 33.866345791607,
    "lon": -84.118536737243
  },
  {
    "precinct": "093",
    "name": "Cates M",
    "location": "Craig Elementary (GCPS)",
    "address": "1075 Rocky Road",
    "city": "Lawrenceville",
    "state": "GA",
    "zip": "30044",
    "full_address": "1075 Rocky Road, Lawrenceville, GA 30044",
    "lat": 33.902073905879,
    "lon": -84.014414588525
  },
  {
    "precinct": "094",
    "name": "Cates N",
    "location": "Pharr Elementary (GCPS)",
    "address": "1500 North Road",
    "city": "Snellville",
    "state": "GA",
    "zip": "30078",
    "full_address": "1500 North Road, Snellville, GA 30078",
    "lat": 33.891045371238,
    "lon": -84.006306229416
  },
  {
    "precinct": "095",
    "name": "Duluth F",
    "location": "Mason Elementary (GCPS)",
    "address": "3030 Bunten Rd",
    "city": "Duluth",
    "state": "GA",
    "zip": "30096",
    "full_address": "3030 Bunten Rd, Duluth, GA 30096",
    "lat": 33.993659838281,
    "lon": -84.119313018896
  },
  {
    "precinct": "096",
    "name": "Duluth G",
    "location": "B.B.Harris Elementary (GCPS)",
    "address": "3123 Claiborne Drive",
    "city": "Duluth",
    "state": "GA",
    "zip": "30096",
    "full_address": "3123 Claiborne Drive, Duluth, GA 30096",
    "lat": 33.986152426045,
    "lon": -84.13383668779
  },
  {
    "precinct": "097",
    "name": "Goodwins E",
    "location": "Jackson Elementary (GCPS)",
    "address": "1970 Sever Road",
    "city": "Lawrenceville",
    "state": "GA",
    "zip": "30043",
    "full_address": "1970 Sever Road, Lawrenceville, GA 30043",
    "lat": 33.988527712285,
    "lon": -84.060259393886
  },
  {
    "precinct": "098",
    "name": "Goodwins F",
    "location": "Walnut Grove Elementary (GCPS)",
    "address": "75 Taylor Road",
    "city": "Suwanee",
    "state": "GA",
    "zip": "30024",
    "full_address": "75 Taylor Road, Suwanee, GA 30024",
    "lat": 34.016723762491,
    "lon": -84.023499767016
  },
  {
    "precinct": "099",
    "name": "Pinckneyville T",
    "location": "First Chinese Baptist Church - Atlanta",
    "address": "2525 Gravitt Road",
    "city": "Duluth",
    "state": "GA",
    "zip": "30096",
    "full_address": "2525 Gravitt Road, Duluth, GA 30096",
    "lat": 33.961883117791,
    "lon": -84.159254481939
  },
  {
    "precinct": "100",
    "name": "Suwanee B",
    "location": "George Pierce Park (GC Park)",
    "address": "55 Buford Hwy",
    "city": "Suwanee",
    "state": "GA",
    "zip": "30024",
    "full_address": "55 Buford Hwy, Suwanee, GA 30024",
    "lat": 34.063434389655,
    "lon": -84.06028937846
  },
  {
    "precinct": "101",
    "name": "Pinckneyville U",
    "location": "Winters Chapel United Methodist Church",
    "address": "5105 Winters Chapel Road",
    "city": "Atlanta",
    "state": "GA",
    "zip": "30360",
    "full_address": "5105 Winters Chapel Road, Atlanta, GA 30360",
    "lat": 33.946765049318,
    "lon": -84.269914771934
  },
  {
    "precinct": "102",
    "name": "Pucketts B",
    "location": "Harmony Elementary (GCPS)",
    "address": "3946 S. Bogan Road",
    "city": "Buford",
    "state": "GA",
    "zip": "30519",
    "full_address": "3946 S. Bogan Road, Buford, GA 30519",
    "lat": 34.097743959339,
    "lon": -83.97866174548
  },
  {
    "precinct": "103",
    "name": "Berkshire L",
    "location": "The NETT at BERKMAR",
    "address": "675 Pleasant Hill Road",
    "city": "Lilburn",
    "state": "GA",
    "zip": "30047",
    "full_address": "675 Pleasant Hill Road, Lilburn, GA 30047",
    "lat": 33.916473426781,
    "lon": -84.113719265388
  },
  {
    "precinct": "104",
    "name": "Rockbridge F",
    "location": "Evangel Community Church",
    "address": "3857 Centerville-Rosebud Road",
    "city": "Snellville",
    "state": "GA",
    "zip": "30039",
    "full_address": "3857 Centerville-Rosebud Road, Snellville, GA 30039",
    "lat": 33.804273802371,
    "lon": -84.038451932943
  },
  {
    "precinct": "105",
    "name": "Sugar Hill F",
    "location": "Sugar Hill Elementary (GCPS)",
    "address": "939 Level Creek Road",
    "city": "Sugar Hill",
    "state": "GA",
    "zip": "30518",
    "full_address": "939 Level Creek Road, Sugar Hill, GA 30518",
    "lat": 34.101299519189,
    "lon": -84.040259308063
  },
  {
    "precinct": "106",
    "name": "Suwanee C",
    "location": "Suwanee Service Center (GCPS)",
    "address": "670 Highway 23 NW",
    "city": "Suwanee",
    "state": "GA",
    "zip": "30024",
    "full_address": "670 Highway 23 NW, Suwanee, GA 30024",
    "lat": 34.053,
    "lon": -84.0741
  },
  {
    "precinct": "107",
    "name": "Cates O",
    "location": "Five Forks Middle (GCPS)",
    "address": "3250 River Dr, SW",
    "city": "Lawrenceville",
    "state": "GA",
    "zip": "30044",
    "full_address": "3250 River Dr, SW, Lawrenceville, GA 30044",
    "lat": 33.885309077151,
    "lon": -84.069179771274
  },
  {
    "precinct": "108",
    "name": "Baycreek E",
    "location": "Gracepointe Church of the Nazarene",
    "address": "2900 Rosebud Road",
    "city": "Loganville",
    "state": "GA",
    "zip": "30052",
    "full_address": "2900 Rosebud Road, Loganville, GA 30052",
    "lat": 33.864996305326,
    "lon": -83.956964403869
  },
  {
    "precinct": "109",
    "name": "Berkshire M",
    "location": "Killian Hill Baptist/Christian School",
    "address": "151 Arcado Road",
    "city": "Lilburn",
    "state": "GA",
    "zip": "30047",
    "full_address": "151 Arcado Road, Lilburn, GA 30047",
    "lat": 33.888695654813,
    "lon": -84.111715569502
  },
  {
    "precinct": "110",
    "name": "Martins G",
    "location": "Galilean Baptist Church",
    "address": "1390 Monfort Road",
    "city": "Lawrenceville",
    "state": "GA",
    "zip": "30042",
    "full_address": "1390 Monfort Road, Lawrenceville, GA 30042",
    "lat": 33.943608693098,
    "lon": -84.031328806915
  },
  {
    "precinct": "111",
    "name": "Duluth H",
    "location": "Chattahoochee Elementary (GCPS)",
    "address": "2930 Albion Farm Road",
    "city": "Duluth",
    "state": "GA",
    "zip": "30097",
    "full_address": "2930 Albion Farm Road, Duluth, GA 30097",
    "lat": 34.018995794002,
    "lon": -84.143911491371
  },
  {
    "precinct": "112",
    "name": "Berkshire N",
    "location": "Mountain Park Activity Building (GC Park)",
    "address": "1063 Rockbridge Road",
    "city": "Stone Mountain",
    "state": "GA",
    "zip": "30087",
    "full_address": "1063 Rockbridge Road, Stone Mountain, GA 30087",
    "lat": 33.847107626366,
    "lon": -84.133932722447
  },
  {
    "precinct": "113",
    "name": "Pinckneyville V",
    "location": "Rock Bridge Baptist Church of Norcross Inc",
    "address": "1012 Rockbridge Road",
    "city": "Norcross",
    "state": "GA",
    "zip": "30093",
    "full_address": "1012 Rockbridge Road, Norcross, GA 30093",
    "lat": 33.894724820385,
    "lon": -84.186382351819
  },
  {
    "precinct": "114",
    "name": "Pinckneyville W",
    "location": "Hopewell Baptist Church",
    "address": "182 Hunter Street",
    "city": "Norcross",
    "state": "GA",
    "zip": "30071",
    "full_address": "182 Hunter Street, Norcross, GA 30071",
    "lat": 33.940329041383,
    "lon": -84.223391855267
  },
  {
    "precinct": "115",
    "name": "Martins H",
    "location": "Bethesda Elementary (GCPS)",
    "address": "525 Bethesda School Road",
    "city": "Lawrenceville",
    "state": "GA",
    "zip": "30044",
    "full_address": "525 Bethesda School Road, Lawrenceville, GA 30044",
    "lat": 33.926345361121,
    "lon": -84.084779762043
  },
  {
    "precinct": "116",
    "name": "Martins I",
    "location": "Amazing Grace Lutheran Church",
    "address": "3305 Lawrenceville Hwy",
    "city": "Lawrenceville",
    "state": "GA",
    "zip": "30044",
    "full_address": "3305 Lawrenceville Hwy, Lawrenceville, GA 30044",
    "lat": 33.916903860988,
    "lon": -84.093896757899
  },
  {
    "precinct": "117",
    "name": "Martins J",
    "location": "Kanoheda Elementary (GCPS)",
    "address": "1025 Herrington Road",
    "city": "Lawrenceville",
    "state": "GA",
    "zip": "30044",
    "full_address": "1025 Herrington Road, Lawrenceville, GA 30044",
    "lat": 33.942801487995,
    "lon": -84.081416538992
  },
  {
    "precinct": "118",
    "name": "Garners F",
    "location": "Mountain Park United Methodist Church",
    "address": "1405 Rockbridge Road",
    "city": "Stone Mountain",
    "state": "GA",
    "zip": "30087",
    "full_address": "1405 Rockbridge Road, Stone Mountain, GA 30087",
    "lat": 33.836176423607,
    "lon": -84.129241811507
  },
  {
    "precinct": "119",
    "name": "Berkshire O",
    "location": "Knight Elementary School (GCPS)",
    "address": "401 North River Dr",
    "city": "Lilburn",
    "state": "GA",
    "zip": "30047",
    "full_address": "401 North River Dr, Lilburn, GA 30047",
    "lat": 33.886393578332,
    "lon": -84.103163099744
  },
  {
    "precinct": "120",
    "name": "Berkshire P",
    "location": "Berkmar Middle School (GCPS)",
    "address": "4355 Lawrenceville Hwy",
    "city": "Lilburn",
    "state": "GA",
    "zip": "30047",
    "full_address": "4355 Lawrenceville Hwy, Lilburn, GA 30047",
    "lat": 33.9008968,
    "lon": -84.1262693
  },
  {
    "precinct": "121",
    "name": "Pinckneyville X",
    "location": "Berkeley Lake Elementary School (GCPS)",
    "address": "4300 S Berkeley Lake Rd NW",
    "city": "Duluth",
    "state": "GA",
    "zip": "30096",
    "full_address": "4300 S Berkeley Lake Rd NW, Duluth, GA 30096",
    "lat": 33.979492426485,
    "lon": -84.186249542986
  },
  {
    "precinct": "122",
    "name": "Rockbridge G",
    "location": "Anderson-Livsey Elementary (GCPS)",
    "address": "4521 Centerville Hwy",
    "city": "Snellville",
    "state": "GA",
    "zip": "30039",
    "full_address": "4521 Centerville Hwy, Snellville, GA 30039",
    "lat": 33.772618266432,
    "lon": -84.046889605198
  },
  {
    "precinct": "123",
    "name": "Pinckneyville Y",
    "location": "Iglesia Bautista Nueva Jerusalem",
    "address": "5300 Williams Road",
    "city": "Norcross",
    "state": "GA",
    "zip": "30093",
    "full_address": "5300 Williams Road, Norcross, GA 30093",
    "lat": 33.905559615968,
    "lon": -84.169735712574
  },
  {
    "precinct": "124",
    "name": "Goodwins G",
    "location": "Christ the Lord Lutheran Church",
    "address": "1001 Duluth Hwy",
    "city": "Lawrenceville",
    "state": "GA",
    "zip": "30043",
    "full_address": "1001 Duluth Hwy, Lawrenceville, GA 30043",
    "lat": 33.968410202024,
    "lon": -84.035505872022
  },
  {
    "precinct": "125",
    "name": "Pinckneyville Z",
    "location": "Jones Bridge Park/Good Age Building (GC Park)",
    "address": "4901 E Jones Bridge Road",
    "city": "Norcross",
    "state": "GA",
    "zip": "30092",
    "full_address": "4901 E Jones Bridge Road, Norcross, GA 30092",
    "lat": 33.985505116704,
    "lon": -84.231238584449
  },
  {
    "precinct": "126",
    "name": "Pinckneyville AI",
    "location": "Peachtree Elementary",
    "address": "5995 Crooked Creek Rd",
    "city": "Norcross",
    "state": "GA",
    "zip": "30092",
    "full_address": "5995 Crooked Creek Rd, Norcross, GA 30092",
    "lat": 33.962058526105,
    "lon": -84.236840398159
  },
  {
    "precinct": "127",
    "name": "Lawrenceville J",
    "location": "Saint Marguerite D'Youville Catholic Church",
    "address": "85 Gloster Rd NW",
    "city": "Lawrenceville",
    "state": "GA",
    "zip": "30044",
    "full_address": "85 Gloster Rd NW, Lawrenceville, GA 30044",
    "lat": 33.91771518645,
    "lon": -84.069056395112
  },
  {
    "precinct": "128",
    "name": "Goodwins H",
    "location": "Peachtree Road Baptist Church",
    "address": "142 Old Peachtree Road",
    "city": "Suwanee",
    "state": "GA",
    "zip": "30024",
    "full_address": "142 Old Peachtree Road, Suwanee, GA 30024",
    "lat": 34.036110925517,
    "lon": -84.034407364875
  },
  {
    "precinct": "129",
    "name": "Duncans B",
    "location": "Duncan Creek Elementary (GCPS)",
    "address": "4500 Braselton Hwy",
    "city": "Hoschton",
    "state": "GA",
    "zip": "30548",
    "full_address": "4500 Braselton Hwy, Hoschton, GA 30548",
    "lat": 34.074885279828,
    "lon": -83.873181043955
  },
  {
    "precinct": "130",
    "name": "Suwanee D",
    "location": "Riverside Elementary (GCPS)",
    "address": "5445 Settles Bridge Road",
    "city": "Suwanee",
    "state": "GA",
    "zip": "30024",
    "full_address": "5445 Settles Bridge Road, Suwanee, GA 30024",
    "lat": 34.097666521845,
    "lon": -84.105834902042
  },
  {
    "precinct": "131",
    "name": "Suwanee E",
    "location": "Level Creek UMC - O'Rouke Family Life Center",
    "address": "4844 Suwanee Dam Road",
    "city": "Suwanee",
    "state": "GA",
    "zip": "30024",
    "full_address": "4844 Suwanee Dam Road, Suwanee, GA 30024",
    "lat": 34.082060433265,
    "lon": -84.072944050066
  },
  {
    "precinct": "132",
    "name": "Lawrenceville K",
    "location": "Taylor Elementary (GCPS)",
    "address": "600 Taylor School Drive",
    "city": "Lawrenceville",
    "state": "GA",
    "zip": "30043",
    "full_address": "600 Taylor School Drive, Lawrenceville, GA 30043",
    "lat": 34.009154936725,
    "lon": -83.995553892647
  },
  {
    "precinct": "133",
    "name": "Harbins B",
    "location": "Dyer Elementary School (GCPS)",
    "address": "1707 Hurricane Shoals Road",
    "city": "Dacula",
    "state": "GA",
    "zip": "30019",
    "full_address": "1707 Hurricane Shoals Road, Dacula, GA 30019",
    "lat": 33.996062054112,
    "lon": -83.936492014077
  },
  {
    "precinct": "134",
    "name": "Baycreek F",
    "location": "Chestnut Grove Baptist Church",
    "address": "2299 Rosebud Road",
    "city": "Grayson",
    "state": "GA",
    "zip": "30017",
    "full_address": "2299 Rosebud Road, Grayson, GA 30017",
    "lat": 33.886425363989,
    "lon": -83.959386577747
  },
  {
    "precinct": "135",
    "name": "Pucketts C",
    "location": "Ivy Creek Elementary (GCPS)",
    "address": "3443 Ridge Road",
    "city": "Buford",
    "state": "GA",
    "zip": "30519",
    "full_address": "3443 Ridge Road, Buford, GA 30519",
    "lat": 34.096215809673,
    "lon": -83.938077829225
  },
  {
    "precinct": "136",
    "name": "Hog Mountain C",
    "location": "Philadelphia Romanian Church",
    "address": "581 Old Peachtree Rd.",
    "city": "Lawrenceville",
    "state": "GA",
    "zip": "30043",
    "full_address": "581 Old Peachtree Rd., Lawrenceville, GA 30043",
    "lat": 34.037040392315,
    "lon": -84.011986684444
  },
  {
    "precinct": "137",
    "name": "Rockycreek B",
    "location": "Fort Daniel Elementary School (GCPS)",
    "address": "1725 Auburn Rd",
    "city": "Dacula",
    "state": "GA",
    "zip": "30019",
    "full_address": "1725 Auburn Rd, Dacula, GA 30019",
    "lat": 34.045294140885,
    "lon": -83.922587318619
  },
  {
    "precinct": "138",
    "name": "Duluth I",
    "location": "Hull Middle School (GCPS)",
    "address": "1950 Old Peachtree Road",
    "city": "Duluth",
    "state": "GA",
    "zip": "30097",
    "full_address": "1950 Old Peachtree Road, Duluth, GA 30097",
    "lat": 34.014656074289,
    "lon": -84.104344738864
  },
  {
    "precinct": "139",
    "name": "Martins K",
    "location": "Saint Marguerite D'Youville Catholic Church",
    "address": "85 Gloster Road NW",
    "city": "Lawrenceville",
    "state": "GA",
    "zip": "30044",
    "full_address": "85 Gloster Road NW, Lawrenceville, GA 30044",
    "lat": 33.91771518645,
    "lon": -84.069056395112
  },
  {
    "precinct": "140",
    "name": "Suwanee H",
    "location": "North Gwinnett Church",
    "address": "4973 West Price Rd",
    "city": "Suwanee",
    "state": "GA",
    "zip": "30024",
    "full_address": "4973 West Price Rd, Suwanee, GA 30024",
    "lat": 34.088530862746,
    "lon": -84.071614028288
  },
  {
    "precinct": "141",
    "name": "Sugar Hill G",
    "location": "Sycamore Elementary School",
    "address": "5695 Sycamore Road",
    "city": "Sugar Hill",
    "state": "GA",
    "zip": "30518",
    "full_address": "5695 Sycamore Road, Sugar Hill, GA 30518",
    "lat": 34.126156815289,
    "lon": -84.045773951265
  },
  {
    "precinct": "142",
    "name": "Suwanee F",
    "location": "Suwanee Full Gospel Church",
    "address": "3268 Smithtown Road",
    "city": "Suwanee",
    "state": "GA",
    "zip": "30024",
    "full_address": "3268 Smithtown Road, Suwanee, GA 30024",
    "lat": 34.043051922179,
    "lon": -84.03937439517
  },
  {
    "precinct": "143",
    "name": "Lawrenceville L",
    "location": "Sunrise Baptist Church",
    "address": "3000 Sugarloaf Parkway",
    "city": "Lawrenceville",
    "state": "GA",
    "zip": "30045",
    "full_address": "3000 Sugarloaf Parkway, Lawrenceville, GA 30045",
    "lat": 33.918710586892,
    "lon": -84.00386341371
  },
  {
    "precinct": "144",
    "name": "Lawrenceville M",
    "location": "Gwinnett Co Dept of Water Resources",
    "address": "684 Winder Hwy",
    "city": "Lawrenceville",
    "state": "GA",
    "zip": "30045",
    "full_address": "684 Winder Hwy, Lawrenceville, GA 30045",
    "lat": 33.968337109441,
    "lon": -83.959073664681
  },
  {
    "precinct": "145",
    "name": "Baycreek G",
    "location": "Gracepointe Church of the Nazarene",
    "address": "2900 Rosebud Road",
    "city": "Loganville",
    "state": "GA",
    "zip": "30052",
    "full_address": "2900 Rosebud Road, Loganville, GA 30052",
    "lat": 33.864996305326,
    "lon": -83.956964403869
  },
  {
    "precinct": "146",
    "name": "Baycreek H",
    "location": "W.J. Cooper Elementary School",
    "address": "555 Ozora Rd",
    "city": "Loganville",
    "state": "GA",
    "zip": "30052",
    "full_address": "555 Ozora Rd, Loganville, GA 30052",
    "lat": 33.892785138118,
    "lon": -83.914438853071
  },
  {
    "precinct": "147",
    "name": "Baycreek I",
    "location": "Tabernacle International Church",
    "address": "270 Simonton Road SW",
    "city": "Lawrenceville",
    "state": "GA",
    "zip": "30046",
    "full_address": "270 Simonton Road SW, Lawrenceville, GA 30046",
    "lat": 33.935353411984,
    "lon": -83.977044937438
  },
  {
    "precinct": "148",
    "name": "Berkshire Q",
    "location": "Harmony Grove UMC",
    "address": "50 Harmony Grove Rd",
    "city": "Lilburn",
    "state": "GA",
    "zip": "30047",
    "full_address": "50 Harmony Grove Rd, Lilburn, GA 30047",
    "lat": 33.875770930306,
    "lon": -84.164874886862
  },
  {
    "precinct": "149",
    "name": "Goodwins I",
    "location": "Gwinnett Church of Christ",
    "address": "1736 Sever Road",
    "city": "Lawrenceville",
    "state": "GA",
    "zip": "30043",
    "full_address": "1736 Sever Road, Lawrenceville, GA 30043",
    "lat": 33.981874747577,
    "lon": -84.055649800941
  },
  {
    "precinct": "150",
    "name": "Duluth K",
    "location": "Shorty Howell Park Activity Building (GC Park)",
    "address": "2750 Pleasant Hill Road",
    "city": "Duluth",
    "state": "GA",
    "zip": "30096",
    "full_address": "2750 Pleasant Hill Road, Duluth, GA 30096",
    "lat": 33.973583609967,
    "lon": -84.151127154986
  },
  {
    "precinct": "151",
    "name": "Harbins C",
    "location": "Ebenezer Baptist Church",
    "address": "2570 Harbins Road",
    "city": "Dacula",
    "state": "GA",
    "zip": "30019",
    "full_address": "2570 Harbins Road, Dacula, GA 30019",
    "lat": 33.950495489057,
    "lon": -83.8337051572
  },
  {
    "precinct": "152",
    "name": "Rockycreek C",
    "location": "Grace Baptist Church",
    "address": "2980 Old Peachtree Road",
    "city": "Dacula",
    "state": "GA",
    "zip": "30019",
    "full_address": "2980 Old Peachtree Road, Dacula, GA 30019",
    "lat": 34.010440466106,
    "lon": -83.929270133124
  },
  {
    "precinct": "153",
    "name": "Lawrenceville N",
    "location": "Praise Community Church",
    "address": "329 Grayson Hwy",
    "city": "Lawrenceville",
    "state": "GA",
    "zip": "30046",
    "full_address": "329 Grayson Hwy, Lawrenceville, GA 30046",
    "lat": 33.942924334728,
    "lon": -83.983678891512
  },
  {
    "precinct": "154",
    "name": "Pucketts D",
    "location": "Pucketts Mill Elementary School (GCPS)",
    "address": "2442 South Pucketts Mill Rd",
    "city": "Dacula",
    "state": "GA",
    "zip": "30019",
    "full_address": "2442 South Pucketts Mill Rd, Dacula, GA 30019",
    "lat": 34.064570106374,
    "lon": -83.930945599452
  },
  {
    "precinct": "155",
    "name": "Suwanee G",
    "location": "Epiphany Lutheran Church",
    "address": "1350 Peachtree Industrial Blvd",
    "city": "Suwanee",
    "state": "GA",
    "zip": "30024",
    "full_address": "1350 Peachtree Industrial Blvd, Suwanee, GA 30024",
    "lat": 34.042096593232,
    "lon": -84.097668249498
  },
  {
    "precinct": "156",
    "name": "Baycreek J",
    "location": "Community of Grace Lutheran Church",
    "address": "1200 Athens Highway",
    "city": "Grayson",
    "state": "GA",
    "zip": "30017",
    "full_address": "1200 Athens Highway, Grayson, GA 30017",
    "lat": 33.862564371394,
    "lon": -83.968341372738
  }
]